windchill_metric_config/__init__.py
windchill_metric_config/configurator.py
windchill_metric_config/description.py
windchill_metric_config/lib/__init__.py
windchill_metric_config/lib/services.py
windchill_metric_config/system/__init__.py
windchill_metric_config/system/network.py
windchill_metric_config/system/system.py
windchill_metric_config/windchill/__init__.py
windchill_metric_config/windchill/garbage_collector.py
windchill_metric_config/windchill/memory.py
windchill_metric_config/windchill/method_context.py
windchill_metric_config/windchill/method_server.py
windchill_metric_config/windchill/queue_worker.py
windchill_metric_config/windchill/servlet_requests.py
windchill_metric_config/windchill/sessions.py
windchill_metric_config/windchill/windchill.py
windchill_metric_config-0.0.32.dist-info/LICENSE
windchill_metric_config-0.0.32.dist-info/METADATA
windchill_metric_config-0.0.32.dist-info/WHEEL
windchill_metric_config-0.0.32.dist-info/top_level.txt
windchill_metric_config-0.0.32.dist-info/RECORD
