Metadata-Version: 2.1
Name: windchill-metric-config
Version: 0.0.32
Summary: Config reader for mimamorisan
Home-page: https://gitlab.com/cax-team/mimamori-san
Author: Matthias Hippen
Author-email: hippen@gmx.ch
Project-URL: Bug Tracker, https://gitlab.com/cax-team/mimamori-san
Classifier: Programming Language :: Python :: 3
Classifier: License :: OSI Approved :: MIT License
Classifier: Operating System :: OS Independent
Requires-Python: >=3.6
License-File: LICENSE
Requires-Dist: ruamel.yaml
